darkcoverage/__init__.py
darkcoverage/gui.py
darkcoverage/image_processing.py
darkcoverage/main.py
darkcoverage/widgets/__init__.py
darkcoverage/widgets/image_label.py
darkcoverage/widgets/reference_window.py
darkcoverage/widgets/sliders_window.py
darkcoverage-0.2.1.dist-info/METADATA
darkcoverage-0.2.1.dist-info/WHEEL
darkcoverage-0.2.1.dist-info/entry_points.txt
darkcoverage-0.2.1.dist-info/licenses/LICENSE
darkcoverage-0.2.1.dist-info/RECORD
