Metadata-Version: 2.4
Name: darkcoverage
Version: 0.2.1
Summary: Image threshold analysis tool for measuring coverage
Project-URL: Homepage, https://github.com/TZ387/darkcoverage
Project-URL: Repository, https://github.com/TZ387/darkcoverage
Project-URL: Bug Tracker, https://github.com/TZ387/darkcoverage/issues
Project-URL: Documentation, https://github.com/TZ387/darkcoverage#readme
Author-email: Tilen <tilen.zel@gmail.com>
Maintainer-email: Tilen <tilen.zel@gmail.com>
License: MIT
License-File: LICENSE
Keywords: analysis,coverage,dark,gui,image,pyside6,threshold
Classifier: Development Status :: 3 - Alpha
Classifier: Intended Audience :: End Users/Desktop
Classifier: License :: OSI Approved :: MIT License
Classifier: Operating System :: OS Independent
Classifier: Programming Language :: Python :: 3
Classifier: Topic :: Multimedia :: Graphics :: Editors
Classifier: Topic :: Scientific/Engineering :: Image Processing
Classifier: Topic :: Scientific/Engineering :: Visualization
Requires-Python: >=3.8
Requires-Dist: numpy>=1.22.0
Requires-Dist: pillow>=9.3.0
Requires-Dist: pyside6>=6.4.0
